nncc/__init__.py
nncc/compiler.py
nncc/nncc.dll
nncc-2.0.3.dist-info/licenses/LICENSE
nncc-2.0.3.dist-info/METADATA
nncc-2.0.3.dist-info/WHEEL
nncc-2.0.3.dist-info/top_level.txt
nncc-2.0.3.dist-info/RECORD
