Metadata-Version: 2.4
Name: nncc
Version: 2.0.3
Summary: Neural Network to C Compiler
Author-email: Aadi Srivastava <aadisrivastava.iitm@gmail.com>
Project-URL: Homepage, https://github.com/AadiSrivastava05/nncc-neural-net-2-C
Classifier: Programming Language :: Python :: 3
Classifier: License :: OSI Approved :: MIT License
Classifier: Operating System :: OS Independent
Requires-Python: >=3.7
License-File: LICENSE
Requires-Dist: torch
Requires-Dist: safetensors
Requires-Dist: numpy
Dynamic: license-file
